rig/__init__.py
rig/rig.py
jas-1.0.dist-info/LICENCE.txt
jas-1.0.dist-info/METADATA
jas-1.0.dist-info/WHEEL
jas-1.0.dist-info/top_level.txt
jas-1.0.dist-info/RECORD
